testaroonie/__init__.py
testaroonie/test.py
testaroonie-0.0.0.dist-info/METADATA
testaroonie-0.0.0.dist-info/WHEEL
testaroonie-0.0.0.dist-info/top_level.txt
testaroonie-0.0.0.dist-info/RECORD
