Metadata-Version: 2.1
Name: testaroonie
Version: 0.0.0
Summary: A test package
Home-page: https://github.com/pypa/testaroonie
Author: testaroonie joe
Author-email: testaroonie@gmail.com
Project-URL: Bug Tracker, https://github.com/pypa/testaroonie/testaroonie
Classifier: Programming Language :: Python :: 3
Classifier: License :: OSI Approved :: MIT License
Classifier: Operating System :: OS Independent
Requires-Python: >=3.6
